IteratedLearning/__init__.py
IteratedLearning/version.py
IteratedLearning-0.0.0.1.dist-info/LICENSE
IteratedLearning-0.0.0.1.dist-info/METADATA
IteratedLearning-0.0.0.1.dist-info/WHEEL
IteratedLearning-0.0.0.1.dist-info/top_level.txt
IteratedLearning-0.0.0.1.dist-info/RECORD
